{"metadata": {"dbt_schema_version": "https://schemas.getdbt.com/dbt/catalog/v1.json", "dbt_version": "1.5.0", "generated_at": "2026-03-03T01:41:51.327951Z", "invocation_id": "25b6c21f-fa20-4b66-8bdc-14413d9b7794", "env": {}}, "nodes": {"model.dbt_spacex.fct_launches_performance": {"metadata": {"type": "BASE TABLE", "schema": "public", "name": "fct_launches_performance", "database": "spacex_db", "comment": null, "owner": "admin"}, "columns": {"mission_id": {"type": "text", "index": 1, "name": "mission_id", "comment": null}, "mission_name": {"type": "text", "index": 2, "name": "mission_name", "comment": null}, "launch_date": {"type": "timestamp without time zone", "index": 3, "name": "launch_date", "comment": null}, "is_success": {"type": "boolean", "index": 4, "name": "is_success", "comment": null}, "rocket_id": {"type": "text", "index": 5, "name": "rocket_id", "comment": null}}, "stats": {"has_stats": {"id": "has_stats", "label": "Has Stats?", "value": false, "include": false, "description": "Indicates whether there are statistics for this table"}}, "unique_id": "model.dbt_spacex.fct_launches_performance"}, "model.dbt_spacex.stg_launches": {"metadata": {"type": "VIEW", "schema": "public", "name": "stg_launches", "database": "spacex_db", "comment": null, "owner": "admin"}, "columns": {"mission_id": {"type": "text", "index": 1, "name": "mission_id", "comment": null}, "mission_name": {"type": "text", "index": 2, "name": "mission_name", "comment": null}, "launch_date": {"type": "timestamp without time zone", "index": 3, "name": "launch_date", "comment": null}, "is_success": {"type": "boolean", "index": 4, "name": "is_success", "comment": null}, "rocket_id": {"type": "text", "index": 5, "name": "rocket_id", "comment": null}}, "stats": {"has_stats": {"id": "has_stats", "label": "Has Stats?", "value": false, "include": false, "description": "Indicates whether there are statistics for this table"}}, "unique_id": "model.dbt_spacex.stg_launches"}}, "sources": {"source.dbt_spacex.spacex_api.spacex_launches": {"metadata": {"type": "BASE TABLE", "schema": "raw", "name": "Spacex_launches", "database": "spacex_db", "comment": null, "owner": "admin"}, "columns": {"static_fire_date_utc": {"type": "text", "index": 1, "name": "static_fire_date_utc", "comment": null}, "static_fire_date_unix": {"type": "double precision", "index": 2, "name": "static_fire_date_unix", "comment": null}, "net": {"type": "boolean", "index": 3, "name": "net", "comment": null}, "window": {"type": "double precision", "index": 4, "name": "window", "comment": null}, "rocket": {"type": "text", "index": 5, "name": "rocket", "comment": null}, "success": {"type": "boolean", "index": 6, "name": "success", "comment": null}, "failures": {"type": "text", "index": 7, "name": "failures", "comment": null}, "details": {"type": "text", "index": 8, "name": "details", "comment": null}, "crew": {"type": "text", "index": 9, "name": "crew", "comment": null}, "ships": {"type": "text", "index": 10, "name": "ships", "comment": null}, "capsules": {"type": "text", "index": 11, "name": "capsules", "comment": null}, "payloads": {"type": "text", "index": 12, "name": "payloads", "comment": null}, "launchpad": {"type": "text", "index": 13, "name": "launchpad", "comment": null}, "flight_number": {"type": "bigint", "index": 14, "name": "flight_number", "comment": null}, "name": {"type": "text", "index": 15, "name": "name", "comment": null}, "date_utc": {"type": "text", "index": 16, "name": "date_utc", "comment": null}, "date_unix": {"type": "bigint", "index": 17, "name": "date_unix", "comment": null}, "date_local": {"type": "text", "index": 18, "name": "date_local", "comment": null}, "date_precision": {"type": "text", "index": 19, "name": "date_precision", "comment": null}, "upcoming": {"type": "boolean", "index": 20, "name": "upcoming", "comment": null}, "cores": {"type": "text", "index": 21, "name": "cores", "comment": null}, "auto_update": {"type": "boolean", "index": 22, "name": "auto_update", "comment": null}, "tbd": {"type": "boolean", "index": 23, "name": "tbd", "comment": null}, "launch_library_id": {"type": "text", "index": 24, "name": "launch_library_id", "comment": null}, "id": {"type": "text", "index": 25, "name": "id", "comment": null}, "fairings.reused": {"type": "boolean", "index": 26, "name": "fairings.reused", "comment": null}, "fairings.recovery_attempt": {"type": "boolean", "index": 27, "name": "fairings.recovery_attempt", "comment": null}, "fairings.recovered": {"type": "boolean", "index": 28, "name": "fairings.recovered", "comment": null}, "fairings.ships": {"type": "text", "index": 29, "name": "fairings.ships", "comment": null}, "links.patch.small": {"type": "text", "index": 30, "name": "links.patch.small", "comment": null}, "links.patch.large": {"type": "text", "index": 31, "name": "links.patch.large", "comment": null}, "links.reddit.campaign": {"type": "text", "index": 32, "name": "links.reddit.campaign", "comment": null}, "links.reddit.launch": {"type": "text", "index": 33, "name": "links.reddit.launch", "comment": null}, "links.reddit.media": {"type": "text", "index": 34, "name": "links.reddit.media", "comment": null}, "links.reddit.recovery": {"type": "text", "index": 35, "name": "links.reddit.recovery", "comment": null}, "links.flickr.small": {"type": "text", "index": 36, "name": "links.flickr.small", "comment": null}, "links.flickr.original": {"type": "text", "index": 37, "name": "links.flickr.original", "comment": null}, "links.presskit": {"type": "text", "index": 38, "name": "links.presskit", "comment": null}, "links.webcast": {"type": "text", "index": 39, "name": "links.webcast", "comment": null}, "links.youtube_id": {"type": "text", "index": 40, "name": "links.youtube_id", "comment": null}, "links.article": {"type": "text", "index": 41, "name": "links.article", "comment": null}, "links.wikipedia": {"type": "text", "index": 42, "name": "links.wikipedia", "comment": null}, "fairings": {"type": "double precision", "index": 43, "name": "fairings", "comment": null}}, "stats": {"has_stats": {"id": "has_stats", "label": "Has Stats?", "value": false, "include": false, "description": "Indicates whether there are statistics for this table"}}, "unique_id": "source.dbt_spacex.spacex_api.spacex_launches"}, "source.dbt_spacex.spacex_api.Spacex_launches": {"metadata": {"type": "BASE TABLE", "schema": "raw", "name": "Spacex_launches", "database": "spacex_db", "comment": null, "owner": "admin"}, "columns": {"static_fire_date_utc": {"type": "text", "index": 1, "name": "static_fire_date_utc", "comment": null}, "static_fire_date_unix": {"type": "double precision", "index": 2, "name": "static_fire_date_unix", "comment": null}, "net": {"type": "boolean", "index": 3, "name": "net", "comment": null}, "window": {"type": "double precision", "index": 4, "name": "window", "comment": null}, "rocket": {"type": "text", "index": 5, "name": "rocket", "comment": null}, "success": {"type": "boolean", "index": 6, "name": "success", "comment": null}, "failures": {"type": "text", "index": 7, "name": "failures", "comment": null}, "details": {"type": "text", "index": 8, "name": "details", "comment": null}, "crew": {"type": "text", "index": 9, "name": "crew", "comment": null}, "ships": {"type": "text", "index": 10, "name": "ships", "comment": null}, "capsules": {"type": "text", "index": 11, "name": "capsules", "comment": null}, "payloads": {"type": "text", "index": 12, "name": "payloads", "comment": null}, "launchpad": {"type": "text", "index": 13, "name": "launchpad", "comment": null}, "flight_number": {"type": "bigint", "index": 14, "name": "flight_number", "comment": null}, "name": {"type": "text", "index": 15, "name": "name", "comment": null}, "date_utc": {"type": "text", "index": 16, "name": "date_utc", "comment": null}, "date_unix": {"type": "bigint", "index": 17, "name": "date_unix", "comment": null}, "date_local": {"type": "text", "index": 18, "name": "date_local", "comment": null}, "date_precision": {"type": "text", "index": 19, "name": "date_precision", "comment": null}, "upcoming": {"type": "boolean", "index": 20, "name": "upcoming", "comment": null}, "cores": {"type": "text", "index": 21, "name": "cores", "comment": null}, "auto_update": {"type": "boolean", "index": 22, "name": "auto_update", "comment": null}, "tbd": {"type": "boolean", "index": 23, "name": "tbd", "comment": null}, "launch_library_id": {"type": "text", "index": 24, "name": "launch_library_id", "comment": null}, "id": {"type": "text", "index": 25, "name": "id", "comment": null}, "fairings.reused": {"type": "boolean", "index": 26, "name": "fairings.reused", "comment": null}, "fairings.recovery_attempt": {"type": "boolean", "index": 27, "name": "fairings.recovery_attempt", "comment": null}, "fairings.recovered": {"type": "boolean", "index": 28, "name": "fairings.recovered", "comment": null}, "fairings.ships": {"type": "text", "index": 29, "name": "fairings.ships", "comment": null}, "links.patch.small": {"type": "text", "index": 30, "name": "links.patch.small", "comment": null}, "links.patch.large": {"type": "text", "index": 31, "name": "links.patch.large", "comment": null}, "links.reddit.campaign": {"type": "text", "index": 32, "name": "links.reddit.campaign", "comment": null}, "links.reddit.launch": {"type": "text", "index": 33, "name": "links.reddit.launch", "comment": null}, "links.reddit.media": {"type": "text", "index": 34, "name": "links.reddit.media", "comment": null}, "links.reddit.recovery": {"type": "text", "index": 35, "name": "links.reddit.recovery", "comment": null}, "links.flickr.small": {"type": "text", "index": 36, "name": "links.flickr.small", "comment": null}, "links.flickr.original": {"type": "text", "index": 37, "name": "links.flickr.original", "comment": null}, "links.presskit": {"type": "text", "index": 38, "name": "links.presskit", "comment": null}, "links.webcast": {"type": "text", "index": 39, "name": "links.webcast", "comment": null}, "links.youtube_id": {"type": "text", "index": 40, "name": "links.youtube_id", "comment": null}, "links.article": {"type": "text", "index": 41, "name": "links.article", "comment": null}, "links.wikipedia": {"type": "text", "index": 42, "name": "links.wikipedia", "comment": null}, "fairings": {"type": "double precision", "index": 43, "name": "fairings", "comment": null}}, "stats": {"has_stats": {"id": "has_stats", "label": "Has Stats?", "value": false, "include": false, "description": "Indicates whether there are statistics for this table"}}, "unique_id": "source.dbt_spacex.spacex_api.Spacex_launches"}}, "errors": null}